<?xml version="1.0" encoding="utf-8" ?>
<dwsync>
<file name="001.html" server="D:/USBWebServer/root/" local="130110907516965676" remote="130110907510000000" Dst="0" />
<file name="002.html" server="D:/USBWebServer/root/" local="130110907516995678" remote="130110907510000000" Dst="0" />
<file name="003.html" server="D:/USBWebServer/root/" local="130110907517045681" remote="130110907510000000" Dst="0" />
<file name="004.html" server="D:/USBWebServer/root/" local="130110907517085683" remote="130110907510000000" Dst="0" />
<file name="005.html" server="D:/USBWebServer/root/" local="130110907517115685" remote="130110907510000000" Dst="0" />
<file name="006.html" server="D:/USBWebServer/root/" local="130110907517155687" remote="130110907510000000" Dst="0" />
<file name="007.html" server="D:/USBWebServer/root/" local="130110907517185689" remote="130110907510000000" Dst="0" />
<file name="008.html" server="D:/USBWebServer/root/" local="130110907517215691" remote="130110907510000000" Dst="0" />
<file name="009.html" server="D:/USBWebServer/root/" local="130110907517245692" remote="130110907510000000" Dst="0" />
<file name="010.html" server="D:/USBWebServer/root/" local="130110907517275694" remote="130110907510000000" Dst="0" />
<file name="011.html" server="D:/USBWebServer/root/" local="130110907517305696" remote="130110907510000000" Dst="0" />
<file name="012.html" server="D:/USBWebServer/root/" local="130110907517335697" remote="130110907510000000" Dst="0" />
<file name="013.html" server="D:/USBWebServer/root/" local="130110907517365699" remote="130110907510000000" Dst="0" />
<file name="header.html" server="D:/USBWebServer/root/" local="130110907517395701" remote="130110907510000000" Dst="0" />
<file name="license.html" server="D:/USBWebServer/root/" local="130110907517615713" remote="130110907510000000" Dst="0" />
<file name="suggestions.html" server="D:/USBWebServer/root/" local="130110907517645715" remote="130110907510000000" Dst="0" />
<file name="toc.html" server="D:/USBWebServer/root/" local="130110907517675717" remote="130110907510000000" Dst="0" />
</dwsync>